{
  "id": "lesson-practice-undo-redo-practice",
  "version": 1,
  "name": "Undo Redo Practice",
  "metadata": {
    "revision": 1,
    "author": "VIM Master Team",
    "githubUsername": "vimmaster",
    "created": "2026-07-09",
    "difficulty": "beginner",
    "tags": [
      "practice",
      "undo-redo"
    ],
    "estimatedTime": 60,
    "prerequisites": [],
    "learningObjectives": [],
    "order": 113
  },
  "instructions": "Make some changes, then use u to undo them, and Ctrl+r to redo. Practice the undo/redo cycle.",
  "initialContent": [
    "Original text that will be modified",
    "Change this line and then undo it",
    "Practice undoing and redoing changes",
    "Master the undo/redo workflow"
  ],
  "target": {
    "row": 0,
    "col": 0
  },
  "focusCommand": "u",
  "initialCursor": {
    "row": 1,
    "col": 0
  },
  "solution": [
    "d",
    "d",
    "u",
    "g",
    "g"
  ]
}
